pyslac/__init__.py
pyslac/enums.py
pyslac/environment.py
pyslac/examples/__init__.py
pyslac/examples/cs_configuration.json
pyslac/examples/ev_slac_scapy.py
pyslac/examples/multiple_slac_sessions.py
pyslac/examples/single_slac_session.py
pyslac/layer_2_headers.py
pyslac/messages.py
pyslac/session.py
pyslac/sockets/__init__.py
pyslac/sockets/async_linux_socket.py
pyslac/sockets/enums.py
pyslac/utils.py
pyslac-0.8.3.dist-info/LICENSE
pyslac-0.8.3.dist-info/WHEEL
pyslac-0.8.3.dist-info/METADATA
pyslac-0.8.3.dist-info/RECORD
