Metadata-Version: 2.1
Name: pyslac
Version: 0.8.3
Summary: SLAC Protocol implementation, defined in ISO15118-3
Author: André Duarte
Author-email: andre@switch-ev.com, andre14x@gmail.com
Requires-Python: >=3.7,<4.0
Classifier: Programming Language :: Python :: 3
Classifier: Programming Language :: Python :: 3.7
Classifier: Programming Language :: Python :: 3.8
Classifier: Programming Language :: Python :: 3.9
Classifier: Programming Language :: Python :: 3.10
Requires-Dist: environs (>=9.5.0,<10.0.0)
